readwise/__init__.py
readwise/__main__.py
readwise/api.py
readwise/cli.py
readwise/model.py
readwise/py.typed
readwise/version.py
readwise_api-0.3.0.dist-info/LICENSE
readwise_api-0.3.0.dist-info/METADATA
readwise_api-0.3.0.dist-info/WHEEL
readwise_api-0.3.0.dist-info/entry_points.txt
readwise_api-0.3.0.dist-info/RECORD
