Metadata-Version: 2.1
Name: readwise-api
Version: 0.3.0
Summary: An unofficial Python client for the Readwise Reader API.
License: MIT
Author: Florian Schäfer
Author-email: florian.joh.schaefer@gmail.com
Requires-Python: >=3.11,<4.0
Classifier: License :: OSI Approved :: MIT License
Classifier: Programming Language :: Python :: 3
Classifier: Programming Language :: Python :: 3.11
Requires-Dist: pydantic (>=1.10.8,<2.0.0)
Requires-Dist: python-dotenv (>=1.0.0,<2.0.0)
Requires-Dist: requests (>=2.31.0,<3.0.0)
Requires-Dist: typer (>=0.9.0,<0.10.0)
